anycrc/__init__.py
anycrc/__main__.py
anycrc/crc.cpython-310-aarch64-linux-gnu.so
anycrc/crc.pyx
anycrc/models.py
anycrc/utils.py
anycrc-1.3.6.dist-info/METADATA
anycrc-1.3.6.dist-info/WHEEL
anycrc-1.3.6.dist-info/top_level.txt
anycrc-1.3.6.dist-info/RECORD
anycrc-1.3.6.dist-info/licenses/LICENSE
