Metadata-Version: 2.4
Name: anycrc
Version: 1.3.6
Summary: The fastest general Python CRC Library
License: Zlib
Project-URL: Homepage, https://github.com/marzooqy/anycrc
Requires-Python: >=3.8
License-File: LICENSE
Requires-Dist: bitarray==3.7.2
Dynamic: license-file
